metagym/__init__.py
metagym/liftsim/__init__.py
metagym/liftsim/config.ini
metagym/liftsim/environment/__init__.py
metagym/liftsim/environment/env.py
metagym/liftsim/environment/animation/__init__.py
metagym/liftsim/environment/animation/rendering.py
metagym/liftsim/environment/animation/resources/1.png
metagym/liftsim/environment/animation/resources/2.png
metagym/liftsim/environment/animation/resources/3.png
metagym/liftsim/environment/animation/resources/4.png
metagym/liftsim/environment/animation/resources/__init__.py
metagym/liftsim/environment/animation/resources/background.png
metagym/liftsim/environment/animation/resources/down.png
metagym/liftsim/environment/animation/resources/line.png
metagym/liftsim/environment/animation/resources/steady.png
metagym/liftsim/environment/animation/resources/up.png
metagym/liftsim/environment/mansion/__init__.py
metagym/liftsim/environment/mansion/elevator.py
metagym/liftsim/environment/mansion/mansion_config.py
metagym/liftsim/environment/mansion/mansion_manager.py
metagym/liftsim/environment/mansion/test_elevator.py
metagym/liftsim/environment/mansion/utils.py
metagym/liftsim/environment/mansion/person_generators/__init__.py
metagym/liftsim/environment/mansion/person_generators/custom_generator.py
metagym/liftsim/environment/mansion/person_generators/generator_proxy.py
metagym/liftsim/environment/mansion/person_generators/mansion_flow.npy
metagym/liftsim/environment/mansion/person_generators/person_generator.py
metagym/liftsim/environment/mansion/person_generators/uniform_generator.py
metagym/metalocomotion/__init__.py
metagym/metalocomotion/demo.py
metagym/metalocomotion/test.py
metagym/metalocomotion/envs/__init__.py
metagym/metalocomotion/envs/assets/Ants_demo.png
metagym/metalocomotion/envs/assets/Humanoids_demo.png
metagym/metalocomotion/envs/assets/ants/ant.xml
metagym/metalocomotion/envs/assets/ants/ant_var_ood_000.xml
metagym/metalocomotion/envs/assets/ants/ant_var_ood_001.xml
metagym-0.1.1.dist-info/LICENSE
metagym-0.1.1.dist-info/METADATA
metagym-0.1.1.dist-info/WHEEL
metagym-0.1.1.dist-info/top_level.txt
metagym-0.1.1.dist-info/RECORD
